pyrff/__init__.py
pyrff/exceptions.py
pyrff/rff.py
pyrff/test_exceptions.py
pyrff/test_rff.py
pyrff/test_thompson.py
pyrff/test_utils.py
pyrff/thompson.py
pyrff/utils.py
pyrff-2.0.3.dist-info/LICENSE
pyrff-2.0.3.dist-info/METADATA
pyrff-2.0.3.dist-info/WHEEL
pyrff-2.0.3.dist-info/top_level.txt
pyrff-2.0.3.dist-info/RECORD
