Metadata-Version: 2.2
Name: pyrff
Version: 2.0.3
Summary: Implementation of random fourier feature (RFF) approximations and Thompson sampling.
Author-email: Michael Osthege <michael.osthege@outlook.com>
License: GNU Affero General Public License v3
Classifier: Programming Language :: Python
Classifier: Operating System :: OS Independent
Classifier: Programming Language :: Python :: 3.10
Classifier: Programming Language :: Python :: 3.11
Classifier: Programming Language :: Python :: 3.12
Classifier: Intended Audience :: Science/Research
Classifier: License :: OSI Approved :: GNU Affero General Public License v3
Classifier: Topic :: Scientific/Engineering :: Mathematics
Requires-Python: >=3.10
License-File: LICENSE
Requires-Dist: h5py
Requires-Dist: numba
Requires-Dist: numpy
Requires-Dist: rich
Requires-Dist: scipy
